mezzanine_client/__init__.py
mezzanine_client/api.py
mezzanine_client/cli.py
mezzanine_client/config.py
mezzanine_client/errors.py
mezzanine_client/utils.py
mezzanine_client-0.2.2.dist-info/DESCRIPTION.rst
mezzanine_client-0.2.2.dist-info/METADATA
mezzanine_client-0.2.2.dist-info/RECORD
mezzanine_client-0.2.2.dist-info/WHEEL
mezzanine_client-0.2.2.dist-info/entry_points.txt
mezzanine_client-0.2.2.dist-info/metadata.json
mezzanine_client-0.2.2.dist-info/top_level.txt
