Metadata-Version: 2.0
Name: mezzanine-client
Version: 0.2.2
Summary: A remote CLI and Python client SDK for Mezzanine REST API.
Home-page: http://gcushen.github.io/mezzanine-api/client/
Author: George Cushen
Author-email: mezzanine-users@googlegroups.com
License: ISC
Keywords: mezzanine cms api client sdk library rest restful
Platform: UNKNOWN
Classifier: Development Status :: 4 - Beta
Classifier: Environment :: Console
Classifier: Intended Audience :: Developers
Classifier: License :: OSI Approved :: ISC License (ISCL)
Classifier: Operating System :: OS Independent
Classifier: Programming Language :: Python
Classifier: Programming Language :: Python :: 2.7
Classifier: Programming Language :: Python :: 3
Classifier: Programming Language :: Python :: 3.5
Classifier: Topic :: Internet :: WWW/HTTP
Classifier: Topic :: Internet :: WWW/HTTP :: Site Management
Classifier: Topic :: Software Development :: Libraries :: Python Modules
Requires-Dist: click
Requires-Dist: future
Requires-Dist: markdown2
Requires-Dist: requests (>=2.9.1)
Requires-Dist: requests-oauthlib (>=0.6.1)
